mapreg/__init__.py
mapreg/prep_for_registration.py
mapreg/register_maps.py
mapreg-0.0.4.dist-info/LICENSE
mapreg-0.0.4.dist-info/METADATA
mapreg-0.0.4.dist-info/WHEEL
mapreg-0.0.4.dist-info/entry_points.txt
mapreg-0.0.4.dist-info/top_level.txt
mapreg-0.0.4.dist-info/RECORD
